llama_index/retrievers/videodb/__init__.py
llama_index/retrievers/videodb/base.py
llama_index_retrievers_videodb-0.4.1.dist-info/METADATA
llama_index_retrievers_videodb-0.4.1.dist-info/WHEEL
llama_index_retrievers_videodb-0.4.1.dist-info/licenses/LICENSE
llama_index_retrievers_videodb-0.4.1.dist-info/RECORD
