Metadata-Version: 2.4
Name: llama-index-retrievers-videodb
Version: 0.4.1
Summary: llama-index VideoDB Retriever integration
Author-email: VideoDB <ashu@videodb.io>
Maintainer-email: Rohit Garg <rohit@videodb.io>
License-Expression: MIT
License-File: LICENSE
Requires-Python: <4.0,>=3.9
Requires-Dist: llama-index-core<0.15,>=0.13.0
Requires-Dist: videodb>=0.2.0
